SWIPL_wrapper/SWIPL_wrapper.py
SWIPL_wrapper/__init__.py
functional_swipl_interface-1.0.1.dist-info/LICENSE
functional_swipl_interface-1.0.1.dist-info/METADATA
functional_swipl_interface-1.0.1.dist-info/WHEEL
functional_swipl_interface-1.0.1.dist-info/top_level.txt
functional_swipl_interface-1.0.1.dist-info/RECORD
