Metadata-Version: 2.1
Name: functional-swipl-interface
Version: 1.0.1
Summary: A wrapper built on top of the official SWI-Prolog Python interface to iteract with prolog through python using a functional programming paradigm. This wrapper is specifically designed to facilitate programmers with no prior knowledge of logic programming to interact with Prolog
Home-page: https://github.com/levshuster/functional-swipl-interface
Author: Lev Shuster
Author-email: Shusterlev@gmail.com
License: MIT
License-File: LICENSE
Requires-Dist: swiplserver
